{
    "Ar36": {
        "error": 0.00032669510893514037,
        "error_type": "SEM",
        "filter_outliers_dict": {
            "filter_outliers": false,
            "iterations": 1,
            "std_devs": 2,
            "use_iqr_filtering": false,
            "use_standard_deviation_filtering": false
        },
        "fit": "Linear",
        "fn": 150,
        "include_baseline_error": false,
        "n": 150,
        "outlier_excluded": [],
        "reviewed": true,
        "user_excluded": [],
        "value": 0.011074640352799309
    },
    "Ar37": {
        "error": 0.009640081899827246,
        "error_type": "SEM",
        "filter_outliers_dict": {
            "filter_outliers": true,
            "iterations": 1,
            "std_devs": 2
        },
        "fit": "Linear",
        "value": -0.00800617315404229
    },
    "Ar38": {
        "error": 0.012311070782965528,
        "error_type": "SEM",
        "filter_outliers_dict": {
            "filter_outliers": false,
            "iterations": 0,
            "std_devs": 0,
            "use_iqr_filtering": false,
            "use_standard_deviation_filtering": false
        },
        "fit": "Linear",
        "fn": 150,
        "include_baseline_error": false,
        "n": 150,
        "outlier_excluded": [],
        "reviewed": true,
        "user_excluded": [],
        "value": 0.1274708802427245
    },
    "Ar39": {
        "error": 0.011362900497373898,
        "error_type": "SEM",
        "filter_outliers_dict": {
            "filter_outliers": false,
            "iterations": 0,
            "std_devs": 0,
            "use_iqr_filtering": false,
            "use_standard_deviation_filtering": false
        },
        "fit": "Linear",
        "fn": 150,
        "include_baseline_error": false,
        "n": 150,
        "outlier_excluded": [],
        "reviewed": true,
        "user_excluded": [],
        "value": 10.062389165325943
    },
    "Ar40": {
        "error": 0.1015115224676208,
        "error_type": "SEM",
        "filter_outliers_dict": {
            "filter_outliers": false,
            "iterations": 0,
            "std_devs": 0,
            "use_iqr_filtering": false,
            "use_standard_deviation_filtering": false
        },
        "fit": "Linear",
        "fn": 150,
        "include_baseline_error": false,
        "n": 150,
        "outlier_excluded": [],
        "reviewed": true,
        "user_excluded": [],
        "value": 1240.0771277786503
    }
}