{
    "Ar36": {
        "error": 0.001673820020068615,
        "error_type": "SEM",
        "filter_outliers_dict": {
            "filter_outliers": false,
            "iterations": 0,
            "std_devs": 0,
            "use_standard_deviation_filtering": false
        },
        "fit": "Linear",
        "fn": 150,
        "include_baseline_error": false,
        "n": 150,
        "outlier_excluded": [],
        "reviewed": true,
        "user_excluded": [],
        "value": 0.01865823662032659
    },
    "Ar37": {
        "error": 0.009919969795754404,
        "error_type": "SEM",
        "filter_outliers_dict": {
            "filter_outliers": true,
            "iterations": 1,
            "std_devs": 2
        },
        "fit": "Linear",
        "value": -0.012743819495310373
    },
    "Ar38": {
        "error": 0.05873208088935273,
        "error_type": "SEM",
        "filter_outliers_dict": {
            "filter_outliers": false,
            "iterations": 0,
            "std_devs": 0,
            "use_standard_deviation_filtering": false
        },
        "fit": "Linear",
        "fn": 150,
        "include_baseline_error": false,
        "n": 150,
        "outlier_excluded": [],
        "reviewed": true,
        "user_excluded": [],
        "value": 0.07516253366364231
    },
    "Ar39": {
        "error": 0.05861625531403224,
        "error_type": "SEM",
        "filter_outliers_dict": {
            "filter_outliers": false,
            "iterations": 0,
            "std_devs": 0,
            "use_standard_deviation_filtering": false
        },
        "fit": "Linear",
        "fn": 150,
        "include_baseline_error": false,
        "n": 150,
        "outlier_excluded": [],
        "reviewed": true,
        "user_excluded": [],
        "value": 5.721657284570863
    },
    "Ar40": {
        "error": 0.3419793546945276,
        "error_type": "SEM",
        "filter_outliers_dict": {
            "filter_outliers": false,
            "iterations": 0,
            "std_devs": 0,
            "use_standard_deviation_filtering": false
        },
        "fit": "Linear",
        "fn": 150,
        "include_baseline_error": false,
        "n": 150,
        "outlier_excluded": [],
        "reviewed": true,
        "user_excluded": [],
        "value": 710.3556858770537
    }
}